_zlib_state.cpython-39-x86_64-linux-gnu.so
zlib_state/__init__.py
zlib_state-0.1.10.dist-info/METADATA
zlib_state-0.1.10.dist-info/WHEEL
zlib_state-0.1.10.dist-info/top_level.txt
zlib_state-0.1.10.dist-info/RECORD
zlib_state-0.1.10.dist-info/licenses/LICENSE
