Metadata-Version: 2.1
Name: zlib-state
Version: 0.1.10
Summary: Low-level interface to the zlib library that enables capturing the decoding state
Home-page: https://github.com/seanmacavaney/zlib-state
Author: Sean MacAvaney
Author-email: sean.macavaney@gmail.com
Classifier: License :: OSI Approved :: MIT License
Requires-Python: >=3.6
License-File: LICENSE
